pyror/__init__.py
pyror/request.py
pyror/ror.py
pyror/utils.py
pyror/scripts/__init__.py
pyror/scripts/rorid.py
test/__init__.py
test/test-ror_id.py
test/test-ror_match.py
test/test-ror_search.py
pyror-0.1.0.dist-info/LICENSE
pyror-0.1.0.dist-info/METADATA
pyror-0.1.0.dist-info/WHEEL
pyror-0.1.0.dist-info/entry_points.txt
pyror-0.1.0.dist-info/top_level.txt
pyror-0.1.0.dist-info/RECORD
