Metadata-Version: 2.1
Name: pyror
Version: 0.1.0
Summary: Research Organization Registry Python Client
Home-page: https://github.com/sckott/pyror
Author: Scott Chamberlain
Author-email: myrmecocystus@gmail.com
License: MIT
Platform: UNKNOWN
Classifier: Development Status :: 3 - Alpha
Classifier: Natural Language :: English
Classifier: License :: OSI Approved :: MIT License
Classifier: Programming Language :: Python
Classifier: Programming Language :: Python :: 3
License-File: LICENSE
Requires-Dist: requests
Requires-Dist: Click
